workutils/__init__.py
workutils/workutils.py
workutils-0.1.0.dist-info/LICENSE
workutils-0.1.0.dist-info/METADATA
workutils-0.1.0.dist-info/WHEEL
workutils-0.1.0.dist-info/entry_points.txt
workutils-0.1.0.dist-info/top_level.txt
workutils-0.1.0.dist-info/RECORD
