Metadata-Version: 2.1
Name: workutils
Version: 0.1.0
Summary: A tool to solve daily work.
Home-page: https://github.com/ldspdvsun/workutils
Author: MengYue Sun
Author-email: ldspdvsun@gmail.com
License: MIT
Classifier: License :: OSI Approved :: MIT License
Classifier: Programming Language :: Python
Classifier: Programming Language :: Python :: 3
Classifier: Programming Language :: Python :: 3.8
Classifier: Programming Language :: Python :: Implementation :: CPython
Classifier: Programming Language :: Python :: Implementation :: PyPy
Requires-Python: >=3.8.0
License-File: LICENSE
Requires-Dist: chardet
